mcp2serial/__init__.py
mcp2serial/server.py
mcp2serial-0.1.3.dist-info/METADATA
mcp2serial-0.1.3.dist-info/WHEEL
mcp2serial-0.1.3.dist-info/entry_points.txt
mcp2serial-0.1.3.dist-info/licenses/LICENSE
mcp2serial-0.1.3.dist-info/RECORD
