Metadata-Version: 2.4
Name: mcp2serial
Version: 0.1.3
Summary: MCP Serial Service for PWM Control
Project-URL: Homepage, https://github.com/mcp2everything/mcp2serial
Project-URL: Documentation, https://github.com/mcp2everything/mcp2serial/tree/main/docs
Project-URL: Repository, https://github.com/mcp2everything/mcp2serial.git
Project-URL: Issues, https://github.com/mcp2everything/mcp2serial/issues
Author: MCP2Everything Team
License-Expression: MIT
License-File: LICENSE
Keywords: ai,llm,mcp,pwm,serial
Classifier: Development Status :: 4 - Beta
Classifier: Intended Audience :: Developers
Classifier: License :: OSI Approved :: MIT License
Classifier: Programming Language :: Python :: 3
Classifier: Programming Language :: Python :: 3.11
Classifier: Topic :: Scientific/Engineering
Classifier: Topic :: Software Development :: Libraries :: Python Modules
Classifier: Topic :: System :: Hardware
Requires-Python: >=3.11
Requires-Dist: mcp>=1.1.2
Requires-Dist: pyserial>=3.5
Requires-Dist: pyyaml>=6.0.1
Provides-Extra: dev
Requires-Dist: pytest>=7.0; extra == 'dev'
